scm_modules/__init__.py
scm_modules/__main__.py
scm_modules/metrics/__init__.py
scm_modules/metrics/abstractness_metric.py
scm_modules/metrics/distance_ia.py
scm_modules/metrics/instability_metric.py
scm_modules/metrics/main_sequence.py
scm_modules/utils/DataSeriesUtility.py
scm_modules/utils/FileUtility.py
scm_modules/utils/ProgrammingLanguageConfig.py
scm_modules/utils/ProgrammingLanguageConstants.py
scm_modules/utils/__init__.py
staticcodemetric_scm_pkg-1.0.3.dist-info/LICENSE
staticcodemetric_scm_pkg-1.0.3.dist-info/METADATA
staticcodemetric_scm_pkg-1.0.3.dist-info/WHEEL
staticcodemetric_scm_pkg-1.0.3.dist-info/entry_points.txt
staticcodemetric_scm_pkg-1.0.3.dist-info/top_level.txt
staticcodemetric_scm_pkg-1.0.3.dist-info/RECORD
