Metadata-Version: 2.1
Name: staticcodemetric-scm-pkg
Version: 1.0.3
Summary: A summary of static-code metrics
Home-page: https://github.com/Markus2101/StaticCodeMetrics
Author: Markus Loipfinger
Author-email: m.loipfinger@hotmail.de
License: GPL-3.0
Platform: UNKNOWN
Classifier: Programming Language :: Python :: 3
Classifier: Programming Language :: Python :: 3.7
Requires-Dist: numpy
Requires-Dist: pandas
Requires-Dist: matplotlib
